src/__init__.py
src/main.py
src/tests/__init__.py
src/tests/tests.py
VeldSpec-0.1.1.dist-info/LICENSE
VeldSpec-0.1.1.dist-info/METADATA
VeldSpec-0.1.1.dist-info/WHEEL
VeldSpec-0.1.1.dist-info/top_level.txt
VeldSpec-0.1.1.dist-info/RECORD
