Metadata-Version: 2.1
Name: VeldSpec
Version: 0.1.1
Summary: VELD specification
Home-page: https://github.com/acdh-oeaw/VELD_spec
Author: Stefan Resch
Author-email: stefan.resch@oeaw.aca.t
Classifier: Programming Language :: Python :: 3
Classifier: License :: OSI Approved :: MIT License
Classifier: Operating System :: OS Independent
Requires-Python: >=3.6
License-File: LICENSE
Requires-Dist: PyYAML >=6.0.2
Requires-Dist: jsonschema >=4.23.0
